contracts/Escrow.sol
contracts/EscrowFactory.sol
contracts/HMToken.sol
contracts/HMTokenInterface.sol
contracts/Migrations.sol
contracts/SafeMath.sol
contracts/SkaleStorage.sol
hmt_escrow/__init__.py
hmt_escrow/eth_bridge.py
hmt_escrow/job.py
hmt_escrow/kvstore_abi.py
hmt_escrow/storage.py
hmt_escrow/test_manifest.py
migrations/1_initial_migration.js
migrations/2_deploy_contracts.js
migrations/3_deploy_storage.js
skale_hmt_escrow-0.9.4.dist-info/LICENSE
skale_hmt_escrow-0.9.4.dist-info/METADATA
skale_hmt_escrow-0.9.4.dist-info/WHEEL
skale_hmt_escrow-0.9.4.dist-info/top_level.txt
skale_hmt_escrow-0.9.4.dist-info/zip-safe
skale_hmt_escrow-0.9.4.dist-info/RECORD
