Metadata-Version: 2.1
Name: skale-hmt-escrow
Version: 0.9.4
Summary: A python library to launch escrow contracts to the HUMAN network.
Home-page: https://github.com/humanprotocol/hmt-escrow
Author: HUMAN Protocol
Author-email: UNKNOWN
License: UNKNOWN
Platform: UNKNOWN
Classifier: Intended Audience :: Developers
Classifier: Operating System :: OS Independent
Classifier: Programming Language :: Python
Requires-Dist: hmt-basemodels
Requires-Dist: boto3
